standard/abis/matching_engine.py
standard/addresses/matching_engine.py
standard/setup.py
standard/types/__init__.py
standard/types/orderbook.py
standard/types/trade.py
tests/test_setup.py
standard_py-0.0.0.dist-info/LICENSE
standard_py-0.0.0.dist-info/METADATA
standard_py-0.0.0.dist-info/WHEEL
standard_py-0.0.0.dist-info/RECORD
